{
    "InventoryDateTime": "2017-01-14 00:00:00",
    "Products": [
        {
            "Arrivals": 0,
            "CurrentInventory": [
                {
                    "ExpiryDateTime": "2017-01-15 07:00:00",
                    "Units": 36
                }
            ],
            "Losses": 0,
            "ProductID": "1_1",
            "Sales": 113,
            "Spoilages": 0
        },
        {
            "Arrivals": 0,
            "CurrentInventory": [],
            "Losses": 0,
            "ProductID": "2_1",
            "Sales": 163,
            "Spoilages": 0
        },
        {
            "Arrivals": 0,
            "CurrentInventory": [
                {
                    "ExpiryDateTime": "2017-01-18 07:00:00",
                    "Units": 97
                }
            ],
            "Losses": 0,
            "ProductID": "3_1",
            "Sales": 128,
            "Spoilages": 0
        },
        {
            "Arrivals": 0,
            "CurrentInventory": [
                {
                    "ExpiryDateTime": "2017-01-19 07:00:00",
                    "Units": 1499
                }
            ],
            "Losses": 0,
            "ProductID": "4_1",
            "Sales": 617,
            "Spoilages": 0
        },
        {
            "Arrivals": 0,
            "CurrentInventory": [
                {
                    "ExpiryDateTime": "2017-01-20 07:00:00",
                    "Units": 118
                }
            ],
            "Losses": 0,
            "ProductID": "5_1",
            "Sales": 237,
            "Spoilages": 0
        },
        {
            "Arrivals": 0,
            "CurrentInventory": [
                {
                    "ExpiryDateTime": "2017-01-20 07:00:00",
                    "Units": 630
                }
            ],
            "Losses": 0,
            "ProductID": "6_1",
            "Sales": 222,
            "Spoilages": 0
        },
        {
            "Arrivals": 0,
            "CurrentInventory": [],
            "Losses": 0,
            "ProductID": "7_1",
            "Sales": 0,
            "Spoilages": 0
        },
        {
            "Arrivals": 0,
            "CurrentInventory": [
                {
                    "ExpiryDateTime": "2017-01-14 07:00:00",
                    "Units": 3
                }
            ],
            "Losses": 0,
            "ProductID": "8_1",
            "Sales": 76,
            "Spoilages": 0
        },
        {
            "Arrivals": 0,
            "CurrentInventory": [
                {
                    "ExpiryDateTime": "2017-01-20 07:00:00",
                    "Units": 37
                }
            ],
            "Losses": 0,
            "ProductID": "9_1",
            "Sales": 200,
            "Spoilages": 0
        },
        {
            "Arrivals": 0,
            "CurrentInventory": [],
            "Losses": 0,
            "ProductID": "10_1",
            "Sales": 248,
            "Spoilages": 0
        },
        {
            "Arrivals": 0,
            "CurrentInventory": [],
            "Losses": 0,
            "ProductID": "11_1",
            "Sales": 82,
            "Spoilages": 0
        },
        {
            "Arrivals": 0,
            "CurrentInventory": [],
            "Losses": 0,
            "ProductID": "12_1",
            "Sales": 411,
            "Spoilages": 0
        },
        {
            "Arrivals": 0,
            "CurrentInventory": [],
            "Losses": 0,
            "ProductID": "13_1",
            "Sales": 139,
            "Spoilages": 0
        },
        {
            "Arrivals": 0,
            "CurrentInventory": [
                {
                    "ExpiryDateTime": "2044-05-31 07:00:00",
                    "Units": 23
                }
            ],
            "Losses": 0,
            "ProductID": "14_1",
            "Sales": 132,
            "Spoilages": 0
        },
        {
            "Arrivals": 0,
            "CurrentInventory": [
                {
                    "ExpiryDateTime": "2017-01-16 07:00:00",
                    "Units": 368
                }
            ],
            "Losses": 0,
            "ProductID": "15_1",
            "Sales": 205,
            "Spoilages": 0
        },
        {
            "Arrivals": 0,
            "CurrentInventory": [
                {
                    "ExpiryDateTime": "2044-05-31 07:00:00",
                    "Units": 78
                }
            ],
            "Losses": 0,
            "ProductID": "16_1",
            "Sales": 36,
            "Spoilages": 0
        },
        {
            "Arrivals": 0,
            "CurrentInventory": [
                {
                    "ExpiryDateTime": "2017-01-18 07:00:00",
                    "Units": 164
                }
            ],
            "Losses": 0,
            "ProductID": "17_1",
            "Sales": 600,
            "Spoilages": 0
        },
        {
            "Arrivals": 0,
            "CurrentInventory": [
                {
                    "ExpiryDateTime": "2044-05-31 07:00:00",
                    "Units": 685
                }
            ],
            "Losses": 0,
            "ProductID": "18_1",
            "Sales": 155,
            "Spoilages": 0
        },
        {
            "Arrivals": 0,
            "CurrentInventory": [],
            "Losses": 0,
            "ProductID": "19_1",
            "Sales": 37,
            "Spoilages": 0
        },
        {
            "Arrivals": 0,
            "CurrentInventory": [
                {
                    "ExpiryDateTime": "2044-05-31 07:00:00",
                    "Units": 1145
                }
            ],
            "Losses": 0,
            "ProductID": "20_1",
            "Sales": 889,
            "Spoilages": 0
        }
    ],
    "StoreID": 4
}