{
    "PriceDate": "2017-01-06 00:00:00",
    "PriceUpdates": [
        {
            "Price": 9.18,
            "ProductID": "1_1"
        },
        {
            "Price": 11.14,
            "ProductID": "2_1"
        },
        {
            "Price": 9.46,
            "ProductID": "3_1"
        },
        {
            "Price": 4.39,
            "ProductID": "4_1"
        },
        {
            "Price": 6.76,
            "ProductID": "5_1"
        },
        {
            "Price": 10.22,
            "ProductID": "6_1"
        },
        {
            "Price": 4.7,
            "ProductID": "7_1"
        },
        {
            "Price": 21.5,
            "ProductID": "8_1"
        },
        {
            "Price": 9.36,
            "ProductID": "9_1"
        },
        {
            "Price": 8.11,
            "ProductID": "10_1"
        },
        {
            "Price": 15.39,
            "ProductID": "11_1"
        },
        {
            "Price": 7.14,
            "ProductID": "12_1"
        },
        {
            "Price": 11.06,
            "ProductID": "13_1"
        },
        {
            "Price": 9.05,
            "ProductID": "14_1"
        },
        {
            "Price": 10.74,
            "ProductID": "15_1"
        },
        {
            "Price": 23.31,
            "ProductID": "16_1"
        },
        {
            "Price": 6.89,
            "ProductID": "17_1"
        },
        {
            "Price": 10.07,
            "ProductID": "18_1"
        },
        {
            "Price": 19.68,
            "ProductID": "19_1"
        },
        {
            "Price": 5.64,
            "ProductID": "20_1"
        }
    ],
    "StoreID": 4
}